hazbin_hotel/__init__.py
hazbin_hotel/src/__init__.py
hazbin_hotel/src/enums/__init__.py
hazbin_hotel/src/enums/types.py
hazbin_hotel/src/exceptions/__init__.py
hazbin_hotel/src/exceptions/room/__init__.py
hazbin_hotel/src/exceptions/room/invalid_period_error.py
hazbin_hotel/src/hotel.py
hazbin_hotel/src/period.py
hazbin_hotel/src/room.py
hazbin_hotel/src/schedule.py
hazbin_hotel/src/utils.py
hazbin_hotel-1.0.1.dist-info/METADATA
hazbin_hotel-1.0.1.dist-info/WHEEL
hazbin_hotel-1.0.1.dist-info/RECORD
