Metadata-Version: 2.1
Name: hazbin_hotel
Version: 1.0.1
Summary: 
License: GPL-3.0
Author: Pedro Augusto.
Author-email: pedr.augustobarbosa.aparecido@gmail.com
Requires-Python: >=3.12,<4.0
Classifier: Development Status :: 5 - Production/Stable
Classifier: Environment :: Console
Classifier: License :: OSI Approved :: GNU General Public License v3 (GPLv3)
Classifier: Natural Language :: English
Classifier: Natural Language :: Portuguese (Brazilian)
Classifier: Programming Language :: Python :: 3
Classifier: Programming Language :: Python :: 3.12
Classifier: Programming Language :: Python :: 3.13
Requires-Dist: colorama (>=0.4.6,<0.5.0)
Requires-Dist: ghp-import (>=2.1.0,<3.0.0)
Project-URL: Bug Tracker, https://github.com/PedroLuisDionisioFraga/poetry-and-pytest-usage/issues
Project-URL: Code, https://github.com/PedroLuisDionisioFraga/poetry-and-pytest-usage
Project-URL: Documentation, https://pedroluisdionisiofraga.github.io/poetry-and-pytest-usage/
